{
  "id": "Macebell_Alternating_360_to_Ballistic_Curl",
  "name": "Macebell Alternating 360 to Ballistic Curl",
  "equipment": [
    "Macebell"
  ],
  "movement_patterns": [
    "Rotation"
  ],
  "training_modalities": [],
  "muscle_involvements": [
    {
      "muscle": "PosteriorDeltoid",
      "degree": "PrimeMover"
    },
    {
      "muscle": "BicepsLongHead",
      "degree": "PrimeMover"
    },
    {
      "muscle": "BicepsShortHead",
      "degree": "PrimeMover"
    },
    {
      "muscle": "Brachialis",
      "degree": "Synergist"
    },
    {
      "muscle": "Brachioradialis",
      "degree": "Synergist"
    },
    {
      "muscle": "AnteriorDeltoid",
      "degree": "Synergist"
    },
    {
      "muscle": "LateralDeltoid",
      "degree": "Synergist"
    },
    {
      "muscle": "RotatorCuff",
      "degree": "Stabilizer"
    },
    {
      "muscle": "RectusAbdominis",
      "degree": "Stabilizer"
    },
    {
      "muscle": "Obliques",
      "degree": "Stabilizer"
    },
    {
      "muscle": "TransverseAbdominis",
      "degree": "Stabilizer"
    },
    {
      "muscle": "UpperTrapezius",
      "degree": "Stabilizer"
    },
    {
      "muscle": "WristFlexors",
      "degree": "Stabilizer"
    },
    {
      "muscle": "WristExtensors",
      "degree": "Stabilizer"
    }
  ],
  "primary_joint_actions": [
    "ShoulderHorizontalAbduction",
    "ElbowFlexion"
  ],
  "supporting_joint_actions": [
    "SpinalRotation",
    "ForearmSupination",
    "ScapularRetraction"
  ],
  "is_compound": true,
  "laterality": "Bilateral",
  "is_combination": true,
  "plane_of_motion": [
    "TransversePlane",
    "SagittalPlane"
  ],
  "exercise_style": [
    "Ballistics"
  ],
  "vocabulary_versions": {
    "ontology": "1.0.0",
    "muscles": "0.11.0",
    "movement_patterns": "0.6.0",
    "joint_actions": "0.1.0",
    "modalities": "0.2.0",
    "degrees": "0.2.2",
    "laterality": "1.0.0",
    "planes_of_motion": "1.0.0",
    "exercise_styles": "1.0.0"
  }
}