{
  "id": "Ring_Half_Lay_Back_Lever",
  "name": "Ring Half Lay Back Lever",
  "equipment": [
    "GymnasticRings"
  ],
  "movement_patterns": [
    "IsometricHold",
    "AntiExtension"
  ],
  "training_modalities": [],
  "muscle_involvements": [
    {
      "muscle": "RectusAbdominis",
      "degree": "PrimeMover"
    },
    {
      "muscle": "TransverseAbdominis",
      "degree": "PrimeMover"
    },
    {
      "muscle": "Obliques",
      "degree": "Synergist"
    },
    {
      "muscle": "HipFlexors",
      "degree": "Synergist"
    },
    {
      "muscle": "LatissimusDorsi",
      "degree": "PrimeMover"
    },
    {
      "muscle": "TeresMajor",
      "degree": "Synergist"
    },
    {
      "muscle": "PosteriorDeltoid",
      "degree": "Synergist"
    },
    {
      "muscle": "BicepsLongHead",
      "degree": "Synergist"
    },
    {
      "muscle": "BicepsShortHead",
      "degree": "Synergist"
    },
    {
      "muscle": "Brachialis",
      "degree": "Synergist"
    },
    {
      "muscle": "TricepsLongHead",
      "degree": "Stabilizer"
    },
    {
      "muscle": "TricepsLateralHead",
      "degree": "Stabilizer"
    },
    {
      "muscle": "TricepsMedialHead",
      "degree": "Stabilizer"
    },
    {
      "muscle": "RotatorCuff",
      "degree": "Stabilizer"
    },
    {
      "muscle": "Rhomboids",
      "degree": "Stabilizer"
    },
    {
      "muscle": "LowerTrapezius",
      "degree": "Stabilizer"
    },
    {
      "muscle": "GluteusMaximus",
      "degree": "Stabilizer"
    },
    {
      "muscle": "ErectorSpinae",
      "degree": "Synergist"
    },
    {
      "muscle": "WristFlexors",
      "degree": "Stabilizer"
    }
  ],
  "primary_joint_actions": [
    "SpinalStability"
  ],
  "supporting_joint_actions": [
    "ShoulderExtension",
    "ElbowFlexion",
    "ScapularDepression",
    "ScapularRetraction"
  ],
  "is_compound": true,
  "laterality": "Bilateral",
  "is_combination": false,
  "plane_of_motion": [
    "SagittalPlane"
  ],
  "exercise_style": [
    "Calisthenics"
  ],
  "vocabulary_versions": {
    "ontology": "1.0.0",
    "muscles": "0.11.0",
    "movement_patterns": "0.6.0",
    "joint_actions": "0.1.0",
    "modalities": "0.2.0",
    "degrees": "0.2.2",
    "laterality": "1.0.0",
    "planes_of_motion": "1.0.0",
    "exercise_styles": "1.0.0"
  }
}